sgtnclient/I18N.py
sgtnclient/__init__.py
sgtnclient/sgtn_bykey.py
sgtnclient/sgtn_client.py
sgtnclient/sgtn_debug.py
sgtnclient/sgtn_locale.py
sgtnclient/sgtn_properties.py
sgtnclient/sgtn_py2_base.py
sgtnclient/sgtn_py3_base.py
sgtnclient/sgtn_py_base.py
sgtnclient/sgtn_util.py
zzz001-0.0.4.dist-info/LICENSE
zzz001-0.0.4.dist-info/METADATA
zzz001-0.0.4.dist-info/WHEEL
zzz001-0.0.4.dist-info/top_level.txt
zzz001-0.0.4.dist-info/RECORD
